{
  "lastUpdated": "2025-06-10T23:18:24.487971",
  "totalShows": 10,
  "shows": [
    {
      "timestamp": "250610_2318",
      "htmlFile": "radiox_dashboard_fancy_250610_2318.html",
      "mp3File": "radiox_250610_2318.mp3",
      "pngFile": null,
      "size": 56660,
      "audioSize": 4009342,
      "coverSize": 0
    },
    {
      "timestamp": "250610_2317",
      "htmlFile": "radiox_dashboard_fancy_250610_2317.html",
      "mp3File": "radiox_250610_2317.mp3",
      "pngFile": null,
      "size": 56740,
      "audioSize": 3945394,
      "coverSize": 0
    },
    {
      "timestamp": "250610_2315",
      "htmlFile": "radiox_dashboard_fancy_250610_2315.html",
      "mp3File": null,
      "pngFile": null,
      "size": 56685,
      "audioSize": 0,
      "coverSize": 0
    },
    {
      "timestamp": "250610_2312",
      "htmlFile": "radiox_dashboard_fancy_250610_2312.html",
      "mp3File": null,
      "pngFile": null,
      "size": 56758,
      "audioSize": 0,
      "coverSize": 0
    },
    {
      "timestamp": "250610_2309",
      "htmlFile": "radiox_dashboard_fancy_250610_2309.html",
      "mp3File": null,
      "pngFile": null,
      "size": 56584,
      "audioSize": 0,
      "coverSize": 0
    },
    {
      "timestamp": "250610_2259",
      "htmlFile": "radiox_dashboard_fancy_250610_2259.html",
      "mp3File": null,
      "pngFile": null,
      "size": 56815,
      "audioSize": 0,
      "coverSize": 0
    },
    {
      "timestamp": "250610_2208",
      "htmlFile": "radiox_dashboard_fancy_250610_2208.html",
      "mp3File": null,
      "pngFile": "radiox_250610_2208.png",
      "size": 57323,
      "audioSize": 0,
      "coverSize": 1424652
    },
    {
      "timestamp": "250610_1821",
      "htmlFile": "radiox_dashboard_fancy_250610_1821.html",
      "mp3File": "radiox_250610_1821.mp3",
      "pngFile": "radiox_250610_1821.png",
      "size": 60692,
      "audioSize": 3547459,
      "coverSize": 27962
    },
    {
      "timestamp": "250610_1814",
      "htmlFile": "radiox_dashboard_fancy_250610_1814.html",
      "mp3File": "radiox_250610_1814.mp3",
      "pngFile": "radiox_250610_1814.png",
      "size": 61928,
      "audioSize": 4891388,
      "coverSize": 1711274
    },
    {
      "timestamp": "250610_1813",
      "htmlFile": "radiox_dashboard_fancy_250610_1813.html",
      "mp3File": "radiox_250610_1813.mp3",
      "pngFile": "radiox_250610_1813.png",
      "size": 60504,
      "audioSize": 7080002,
      "coverSize": 1638729
    }
  ]
}